README.md
setup.py
bin/latte
bin/lattestats
latte/Analyzer.py
latte/Base.py
latte/Config.py
latte/Log.py
latte/TimeTracker.py
latte/UserActivityTracker.py
latte/__init__.py
latte/latte.py
latte.egg-info/PKG-INFO
latte.egg-info/SOURCES.txt
latte.egg-info/dependency_links.txt
latte.egg-info/requires.txt
latte.egg-info/top_level.txt
latte/os/__init__.py
latte/os/screen.py