Metadata-Version: 1.0
Name: latte
Version: 4.0
Summary: Automatic rule based Linux Time Tracker
Home-page: https://github.com/flakas/Latte
Author: Tautvidas Sipavicius
Author-email: flakas@tautvidas.com
License: UNKNOWN
Platform: UNKNOWN
